{"cameraMode":{"drawMode":0,"name":"Shaded","section":"Shading Mode"},"sceneLighting":true,"audioPlay":false,"sceneViewState":{"showFog":true,"showMaterialUpdate":false,"showSkybox":true,"showFlares":true,"showImageEffects":true,"showParticleSystems":true},"in2DMode":false,"pivot":{"x":51.94793701171875,"y":20.0584774017334,"z":67.30101013183594},"rotation":{"x":-0.13155090808868409,"y":0.507289707660675,"z":-0.07869367301464081,"w":-0.8480323553085327},"size":3.4818148612976076,"orthographic":false}